{
"type": "FeatureCollection",
"name": "geo_09_短期入所療養介護(療養病床を有する病院等）",
"crs": { "type": "name", "properties": { "name": "urn:ogc:def:crs:OGC:1.3:CRS84" } },
"features": [
{ "type": "Feature", "properties": { "緯度": 36.4415661, "経度": 139.8600664000001, "url": "https://www.kaigokensaku.mhlw.go.jp/09/index.php?action_kouhyou_detail_004_kani=true&JigyosyoCd=0912310489-00&ServiceCd=&Type=search", "url2": "https://tomaruseikei.com/kaigo/", "内容": "医療法人志由会　都丸整形外科　短期入所療養介護【短期入所療養介護(療養病床を有する病院等）】栃木県下野市文教１ー１１ー１６", "サービスの種類": "短期入所療養介護(療養病床を有する病院等）" }, "geometry": { "type": "Point", "coordinates": [ 139.860066400000051, 36.4415661 ] } }
]
}
